antipickle/__init__.py
antipickle/adapters.py
antipickle/adapters_default.py
antipickle/base.py
antipickle/py.typed
antipickle-0.2.0.dist-info/METADATA
antipickle-0.2.0.dist-info/WHEEL
antipickle-0.2.0.dist-info/licenses/LICENSE
antipickle-0.2.0.dist-info/RECORD
