Metadata-Version: 2.3
Name: antipickle
Version: 0.2.0
Summary: Like pickle. But different
Project-URL: Documentation, https://github.com/arogozhnikov/antipickle#readme
Project-URL: Issues, https://github.com/arogozhnikov/antipickle/issues
Project-URL: Source, https://github.com/arogozhnikov/antipickle
Author-email: Alex Rogozhnikov <find.on@my.personal.blog>
License-Expression: MIT
License-File: LICENSE
Classifier: Programming Language :: Python
Classifier: Programming Language :: Python :: 3.7
Classifier: Programming Language :: Python :: 3.8
Classifier: Programming Language :: Python :: 3.9
Classifier: Programming Language :: Python :: 3.10
Classifier: Programming Language :: Python :: 3.11
Requires-Python: >=3.7
Requires-Dist: msgpack>=1.0.4
